setup.py
couchbot/__init__.py
couchbot.egg-info/PKG-INFO
couchbot.egg-info/SOURCES.txt
couchbot.egg-info/dependency_links.txt
couchbot.egg-info/entry_points.txt
couchbot.egg-info/not-zip-safe
couchbot.egg-info/top_level.txt