Metadata-Version: 1.1
Name: couchbot
Version: 0.1.0
Summary: A Slack bot for queuing movies to Couch Potato
Home-page: https://github.com/flaeppe/couchbot
Author: Petter Friberg
Author-email: petter_friberg@hotmail.com
License: MIT
Platform: UNKNOWN
Classifier: Topic :: Utilities
